gfk_models/__init__.py
gfk_models/gfk_base/__init__.py
gfk_models/gfk_base/mixins.py
gfk_models/gfk_base/models.py
gfk_models/gfk_base/views.py
gfk_models/gfk_base/templatetags/__init__.py
gfk_models/gfk_base/templatetags/gfk.py
gfk_models/gfk_helpers/__init__.py
gfk_models/gfk_helpers/functions/__init__.py
gfk_models/gfk_helpers/functions/common.py
gfk_models/gfk_helpers/functions/text_processors.py
gfk_models/gfk_helpers/functions/translitirate.py
gfk_models/like/__init__.py
gfk_models/like/admin.py
gfk_models/like/apps.py
gfk_models/like/mixins.py
gfk_models/like/models.py
gfk_models/like/tests.py
gfk_models/like/urls.py
gfk_models/like/views.py
gfk_models/like/migrations/0001_initial.py
gfk_models/like/migrations/__init__.py
gfk_models/qna/__init__.py
gfk_models/qna/admin.py
gfk_models/qna/forms.py
gfk_models/qna/mixins.py
gfk_models/qna/models.py
gfk_models/qna/tests.py
gfk_models/qna/urls.py
gfk_models/qna/urls_global.py
gfk_models/qna/views.py
gfk_models/qna/migrations/0001_initial.py
gfk_models/qna/migrations/0002_auto_20160424_1425.py
gfk_models/qna/migrations/0003_question__target.py
gfk_models/qna/migrations/0004_question_slug.py
gfk_models/qna/migrations/0005_auto_20160426_0908.py
gfk_models/qna/migrations/0006_answer_accepted.py
gfk_models/qna/migrations/0007_auto_20160429_1128.py
gfk_models/qna/migrations/0008_auto_20160430_1304.py
gfk_models/qna/migrations/0009_auto_20160430_1521.py
gfk_models/qna/migrations/0010_answer_created_at.py
gfk_models/qna/migrations/0011_question_has_answer.py
gfk_models/qna/migrations/0012_auto_20160501_1849.py
gfk_models/qna/migrations/0013_auto_20160914_0857.py
gfk_models/qna/migrations/__init__.py
gfk_models/review/__init__.py
gfk_models/review/admin.py
gfk_models/review/apps.py
gfk_models/review/forms.py
gfk_models/review/mixins.py
gfk_models/review/models.py
gfk_models/review/tests.py
gfk_models/review/urls.py
gfk_models/review/views.py
gfk_models/review/migrations/0001_initial.py
gfk_models-0.0.12.dist-info/LICENSE
gfk_models-0.0.12.dist-info/METADATA
gfk_models-0.0.12.dist-info/WHEEL
gfk_models-0.0.12.dist-info/top_level.txt
gfk_models-0.0.12.dist-info/RECORD
